wb/__init__.py
wb/cli.py
wb_writeupbuilder-2.1.dist-info/licenses/LICENSE
wb_writeupbuilder-2.1.dist-info/METADATA
wb_writeupbuilder-2.1.dist-info/WHEEL
wb_writeupbuilder-2.1.dist-info/entry_points.txt
wb_writeupbuilder-2.1.dist-info/top_level.txt
wb_writeupbuilder-2.1.dist-info/RECORD
