Metadata-Version: 2.4
Name: wb-writeupbuilder
Version: 2.1
Summary: Builds Writup with your input.
Home-page: https://github.com/Ph4nt01/WB-WriteupBuilder
Author: [Ph4nt01]
Author-email: ph4nt0.84@gmail.com
Classifier: Programming Language :: Python :: 3
Classifier: License :: OSI Approved :: MIT License
Requires-Python: >=3.7
License-File: LICENSE
Requires-Dist: colorama
Requires-Dist: prompt_toolkit
Dynamic: author
Dynamic: author-email
Dynamic: classifier
Dynamic: home-page
Dynamic: license-file
Dynamic: requires-dist
Dynamic: requires-python
Dynamic: summary
